.coveragerc
.mailmap
.testr.conf
AUTHORS
CONTRIBUTING.rst
ChangeLog
HACKING.rst
LICENSE
MANIFEST.in
README.rst
babel.cfg
openstack-common.conf
requirements.txt
setup.cfg
setup.py
test-requirements.txt
tox.ini
doc/source/conf.py
doc/source/contributing.rst
doc/source/index.rst
doc/source/installation.rst
doc/source/readme.rst
doc/source/usage.rst
os_performance_tools/__init__.py
os_performance_tools/collect.py
os_performance_tools/counters2statsd.py
os_performance_tools/error.py
os_performance_tools.egg-info/PKG-INFO
os_performance_tools.egg-info/SOURCES.txt
os_performance_tools.egg-info/dependency_links.txt
os_performance_tools.egg-info/entry_points.txt
os_performance_tools.egg-info/not-zip-safe
os_performance_tools.egg-info/pbr.json
os_performance_tools.egg-info/requires.txt
os_performance_tools.egg-info/top_level.txt
os_performance_tools/collectors/__init__.py
os_performance_tools/collectors/_delta.py
os_performance_tools/collectors/mysql.py
os_performance_tools/collectors/queues.py
os_performance_tools/tests/__init__.py
os_performance_tools/tests/base.py
os_performance_tools/tests/test_collect.py
os_performance_tools/tests/test_collectors_delta.py
os_performance_tools/tests/test_counters2statsd.py
os_performance_tools/tests/test_mysql.py
os_performance_tools/tests/test_queues.py